{"version":"0.4","title":"69 &#8211; Tooltip 1","type":"section","content":[{"id":"20db59b","settings":{"gap":"no","margin":{"unit":"px","top":"","right":0,"bottom":"","left":0,"isLinked":true},"margin_tablet":{"unit":"px","top":"","right":0,"bottom":"","left":0,"isLinked":true},"margin_mobile":{"unit":"px","top":"","right":0,"bottom":"","left":0,"isLinked":true},"content_width":{"unit":"px","size":1180,"sizes":[]},"padding":{"unit":"px","top":"140","right":"40","bottom":"140","left":"40","isLinked":false},"padding_tablet":{"unit":"px","top":"120","right":"40","bottom":"120","left":"40","isLinked":false},"padding_mobile":{"unit":"px","top":"100","right":"20","bottom":"100","left":"20","isLinked":false},"content_position":"middle","structure":"30","background_color":"#FAFAFA"},"elements":[{"id":"7db14526","settings":{"_column_size":33,"_inline_size":55,"_inline_size_tablet":100,"space_between_widgets":0,"padding":{"unit":"px","top":"0","right":"100","bottom":"0","left":"0","isLinked":false},"padding_tablet":{"unit":"px","top":"0","right":"0","bottom":"60","left":"0","isLinked":false}},"elements":[{"id":"48d08b43","settings":{"title":"The best places to travel<\/br>in the world","align":"left","typography_typography":"custom","typography_font_family":"Merriweather Sans","typography_font_size":{"unit":"px","size":36,"sizes":[]},"typography_font_weight":"700","_margin":{"unit":"px","top":"0","right":"0","bottom":"10","left":"0","isLinked":false},"_padding":{"unit":"px","top":"0","right":"0","bottom":"0","left":"0","isLinked":true},"typography_font_style":"normal","typography_line_height":{"unit":"em","size":1.3,"sizes":[]},"typography_font_size_tablet":{"unit":"px","size":32,"sizes":[]},"typography_font_size_mobile":{"unit":"px","size":28,"sizes":[]},"title_color":"#212121","link":{"url":"#","is_external":"","nofollow":"","custom_attributes":""},"typography_text_transform":"capitalize"},"elements":[],"isInner":false,"widgetType":"heading","elType":"widget"},{"id":"57ec5914","settings":{"view":"inline","icon_list":[{"text":"John Doe","selected_icon":{"value":"fas fa-user-alt","library":"fa-solid"},"_id":"6feca45","link":{"url":"","is_external":"","nofollow":"","custom_attributes":""}},{"text":"May 21, 2020","selected_icon":{"value":"fas fa-clock","library":"fa-solid"},"_id":"0a86b9f","link":{"url":"","is_external":"","nofollow":"","custom_attributes":""}},{"text":"Travel, Lifestyle","selected_icon":{"value":"fas fa-tag","library":"fa-solid"},"link":{"url":"","is_external":"","nofollow":"","custom_attributes":""},"_id":"acae505"}],"space_between":{"unit":"px","size":20,"sizes":[]},"divider":"yes","divider_color":"#EEEEEE","icon_color":"#51CBCE","text_color":"#212121","icon_typography_typography":"custom","icon_typography_font_family":"Merriweather Sans","icon_typography_font_size":{"unit":"px","size":16,"sizes":[]},"icon_typography_font_weight":"normal","icon_typography_line_height":{"unit":"em","size":1.5,"sizes":[]},"_margin":{"unit":"px","top":"0","right":"0","bottom":"35","left":"0","isLinked":false},"_background_color":"#FAFAFA","icon_typography_font_size_mobile":{"unit":"px","size":15,"sizes":[]}},"elements":[],"isInner":false,"widgetType":"icon-list","elType":"widget"},{"id":"3c74bb9a","settings":{"title":"Lorem ipsum dolor sit amet, consectetur adipiscing elit. Pellentesque lorem fermentum massa vel enim feugiat gravida. Phasellus velit risus, euismod a lacus et, mattis condimentum augue. Vivamus fermentum ex quis imperdiet sodales. Sed aliquam nibh tellus, a rutrum turpis pellentesque ac. Nulla nibh libero, tincidunt cursus gravida ut, sodales ut magna lorem ipsum. Lorem ipsum dolor sit amet augue velit cursus vel massa vel enim.","header_size":"p","title_color":"#757575","typography_typography":"custom","typography_font_family":"Merriweather","typography_font_size":{"unit":"px","size":15,"sizes":[]},"typography_font_weight":"300","typography_font_style":"normal","typography_line_height":{"unit":"em","size":1.7,"sizes":[]},"typography_font_size_mobile":{"unit":"px","size":14,"sizes":[]},"_margin":{"unit":"px","top":"0","right":"0","bottom":"40","left":"0","isLinked":false}},"elements":[],"isInner":false,"widgetType":"heading","elType":"widget"},{"id":"6aea4614","settings":{"text":"READ MORE","icon_switcher":"yes","icon":{"value":"fas fa-long-arrow-alt-right","library":"fa-solid"},"icon_position":"after","icon_spacing":{"unit":"px","top":"0","right":"0","bottom":"0","left":"5","isLinked":false},"typography_typography":"custom","typography_font_family":"Merriweather Sans","typography_font_size":{"unit":"px","size":15,"sizes":[]},"typography_font_weight":"normal","typography_line_height":{"unit":"em","size":1.4,"sizes":[]},"skin":"tme-btn-6","bg_color":"#212121","text_hover_color":"#FFFFFF","bg_hover_color":"#212121","animation_color":"#51CBCE","padding":{"unit":"px","top":"15","right":"20","bottom":"15","left":"20","isLinked":false},"typography_font_size_mobile":{"unit":"px","size":14,"sizes":[]}},"elements":[],"isInner":false,"widgetType":"tme-button","elType":"widget"}],"isInner":false,"elType":"column"},{"id":"1d51fb8b","settings":{"_column_size":33,"_inline_size":22.288,"_inline_size_tablet":50,"content_position":"top","padding":{"unit":"px","top":"0","right":"10","bottom":"0","left":"0","isLinked":false},"padding_mobile":{"unit":"px","top":"0","right":"0","bottom":"0","left":"0","isLinked":true}},"elements":[{"id":"8dc0442","settings":{"content_type":"image","image":{"url":"https:\/\/www.thememasters.club\/assets\/2020\/04\/gallery2.jpg","id":652},"tooltip_content":"<h3>India<\/h3><p>Phasellus velit risus, euismod a lacus et, mattis condimentum augue. Vivamus fermentum ex quis imperdiet sodales.<\/p>","placement":"w","offset":15,"img_border_radius":{"unit":"%","top":"100","right":"100","bottom":"100","left":"100","isLinked":true},"tooltip_heading_typography_typography":"custom","tooltip_heading_typography_font_family":"Merriweather Sans","tooltip_heading_typography_font_size":{"unit":"px","size":22,"sizes":[]},"tooltip_heading_typography_font_weight":"700","tooltip_heading_typography_line_height":{"unit":"em","size":1.2,"sizes":[]},"tooltip_color":"#FFFFFF","tooltip_text_typography_typography":"custom","tooltip_text_typography_font_family":"Merriweather","tooltip_text_typography_font_size":{"unit":"px","size":13,"sizes":[]},"tooltip_text_typography_font_weight":"normal","tooltip_bg_color":"#51CBCE","tooltip_max_width":280,"tooltip_padding":{"unit":"px","top":"25","right":"25","bottom":"25","left":"25","isLinked":true},"tooltip_border_radius":{"unit":"px","top":"10","right":"10","bottom":"10","left":"10","isLinked":true},"tooltip_h_margin":{"unit":"px","top":"0","right":"0","bottom":"10","left":"0","isLinked":false},"tooltip_p_margin":{"unit":"px","top":"0","right":"0","bottom":"0","left":"0","isLinked":true},"max_size":100,"thumbnail_css_filter_saturate":{"unit":"px","size":0,"sizes":[]},"anim":"tada","thumb_radius":{"unit":"px","top":"10","right":"10","bottom":"10","left":"10","isLinked":true},"thumb_shadow_box_shadow":{"horizontal":0,"vertical":2,"blur":5,"spread":0,"color":"rgba(0, 0, 0, 0.3)"},"tooltip_border_shadow_box_shadow_type":"yes","tooltip_border_shadow_box_shadow":{"horizontal":0,"vertical":2,"blur":5,"spread":0,"color":"rgba(0, 0, 0, 0.3)"}},"elements":[],"isInner":false,"widgetType":"tme-tooltip","elType":"widget"},{"id":"3290a999","settings":{"content_type":"image","image":{"url":"https:\/\/www.thememasters.club\/assets\/2020\/04\/gallery4.jpg","id":654},"tooltip_content":"<h3>Italy<\/h3><p>Lorem ipsum dolor sit amet, consectetur adipiscing elit. Pellentesque lorem fermentum massa vel enim feugiat gravida.<\/p>","placement":"w","offset":15,"img_border_radius":{"unit":"%","top":"100","right":"100","bottom":"100","left":"100","isLinked":true},"tooltip_heading_typography_typography":"custom","tooltip_heading_typography_font_family":"Merriweather Sans","tooltip_heading_typography_font_size":{"unit":"px","size":22,"sizes":[]},"tooltip_heading_typography_font_weight":"700","tooltip_heading_typography_line_height":{"unit":"em","size":1.2,"sizes":[]},"tooltip_color":"#FFFFFF","tooltip_text_typography_typography":"custom","tooltip_text_typography_font_family":"Merriweather","tooltip_text_typography_font_size":{"unit":"px","size":13,"sizes":[]},"tooltip_text_typography_font_weight":"normal","tooltip_bg_color":"#51CBCE","tooltip_max_width":260,"tooltip_padding":{"unit":"px","top":"25","right":"25","bottom":"25","left":"25","isLinked":true},"tooltip_border_radius":{"unit":"px","top":"10","right":"10","bottom":"10","left":"10","isLinked":true},"tooltip_h_margin":{"unit":"px","top":"0","right":"0","bottom":"10","left":"0","isLinked":false},"tooltip_p_margin":{"unit":"px","top":"0","right":"0","bottom":"0","left":"0","isLinked":true},"max_size":100,"thumbnail_css_filter_saturate":{"unit":"px","size":0,"sizes":[]},"anim":"rubberBand","thumb_radius":{"unit":"px","top":"10","right":"10","bottom":"10","left":"10","isLinked":true},"tooltip_border_shadow_box_shadow_type":"yes","tooltip_border_shadow_box_shadow":{"horizontal":0,"vertical":2,"blur":5,"spread":0,"color":"rgba(0, 0, 0, 0.3)"}},"elements":[],"isInner":false,"widgetType":"tme-tooltip","elType":"widget"}],"isInner":false,"elType":"column"},{"id":"62fba928","settings":{"_column_size":33,"_inline_size":22.331,"_inline_size_tablet":50,"content_position":"top","padding":{"unit":"px","top":"0","right":"0","bottom":"0","left":"10","isLinked":false},"padding_mobile":{"unit":"px","top":"20","right":"0","bottom":"0","left":"0","isLinked":false}},"elements":[{"id":"5227233f","settings":{"content_type":"image","image":{"url":"https:\/\/www.thememasters.club\/assets\/2020\/04\/gallery3.jpg","id":653},"tooltip_content":"<h3>California<\/h3><p>Phasellus velit risus, euismod a lacus et, mattis condimentum augue. Vivamus fermentum ex quis imperdiet sodales.<\/p>","offset":15,"img_border_radius":{"unit":"%","top":"100","right":"100","bottom":"100","left":"100","isLinked":true},"tooltip_heading_typography_typography":"custom","tooltip_heading_typography_font_family":"Merriweather Sans","tooltip_heading_typography_font_size":{"unit":"px","size":22,"sizes":[]},"tooltip_heading_typography_font_weight":"700","tooltip_heading_typography_line_height":{"unit":"em","size":1.2,"sizes":[]},"tooltip_color":"#FFFFFF","tooltip_text_typography_typography":"custom","tooltip_text_typography_font_family":"Merriweather","tooltip_text_typography_font_size":{"unit":"px","size":13,"sizes":[]},"tooltip_text_typography_font_weight":"normal","tooltip_bg_color":"#51CBCE","tooltip_max_width":280,"tooltip_padding":{"unit":"px","top":"25","right":"25","bottom":"25","left":"25","isLinked":true},"tooltip_border_radius":{"unit":"px","top":"10","right":"10","bottom":"10","left":"10","isLinked":true},"tooltip_h_margin":{"unit":"px","top":"0","right":"0","bottom":"10","left":"0","isLinked":false},"tooltip_p_margin":{"unit":"px","top":"0","right":"0","bottom":"0","left":"0","isLinked":true},"max_size":100,"thumbnail_css_filter_saturate":{"unit":"px","size":0,"sizes":[]},"anim":"bounceInDown","thumb_radius":{"unit":"px","top":"10","right":"10","bottom":"10","left":"10","isLinked":true},"thumb_shadow_box_shadow":{"horizontal":0,"vertical":2,"blur":5,"spread":0,"color":"rgba(0, 0, 0, 0.3)"},"tooltip_border_shadow_box_shadow_type":"yes","tooltip_border_shadow_box_shadow":{"horizontal":0,"vertical":2,"blur":5,"spread":0,"color":"rgba(0, 0, 0, 0.3)"}},"elements":[],"isInner":false,"widgetType":"tme-tooltip","elType":"widget"},{"id":"4222b8f5","settings":{"content_type":"image","image":{"url":"https:\/\/www.thememasters.club\/assets\/2020\/04\/gallery1.jpg","id":651},"tooltip_content":"<h3>Canada<\/h3><p>Lorem ipsum dolor sit amet, consectetur adipiscing elit. Pellentesque lorem fermentum massa vel enim feugiat gravida.<\/p>","placement":"s","offset":15,"img_border_radius":{"unit":"%","top":"100","right":"100","bottom":"100","left":"100","isLinked":true},"tooltip_heading_typography_typography":"custom","tooltip_heading_typography_font_family":"Merriweather Sans","tooltip_heading_typography_font_size":{"unit":"px","size":22,"sizes":[]},"tooltip_heading_typography_font_weight":"700","tooltip_heading_typography_line_height":{"unit":"em","size":1.2,"sizes":[]},"tooltip_color":"#FFFFFF","tooltip_text_typography_typography":"custom","tooltip_text_typography_font_family":"Merriweather","tooltip_text_typography_font_size":{"unit":"px","size":13,"sizes":[]},"tooltip_text_typography_font_weight":"normal","tooltip_bg_color":"#51CBCE","tooltip_max_width":280,"tooltip_padding":{"unit":"px","top":"25","right":"25","bottom":"25","left":"25","isLinked":true},"tooltip_border_radius":{"unit":"px","top":"10","right":"10","bottom":"10","left":"10","isLinked":true},"tooltip_h_margin":{"unit":"px","top":"0","right":"0","bottom":"10","left":"0","isLinked":false},"tooltip_p_margin":{"unit":"px","top":"0","right":"0","bottom":"0","left":"0","isLinked":true},"max_size":100,"thumbnail_css_filter_saturate":{"unit":"px","size":0,"sizes":[]},"anim":"slideInUp","thumb_radius":{"unit":"px","top":"10","right":"10","bottom":"10","left":"10","isLinked":true},"thumb_shadow_box_shadow":{"horizontal":0,"vertical":2,"blur":5,"spread":0,"color":"rgba(0, 0, 0, 0.3)"},"tooltip_border_shadow_box_shadow_type":"yes","tooltip_border_shadow_box_shadow":{"horizontal":0,"vertical":2,"blur":5,"spread":0,"color":"rgba(0, 0, 0, 0.3)"}},"elements":[],"isInner":false,"widgetType":"tme-tooltip","elType":"widget"}],"isInner":false,"elType":"column"}],"isInner":false,"elType":"section"}]}